{"date": "Mon Feb 13 19:08:29 2017", "path": "See-through A Studio", "albums": [], "photos": [{"exposureTime": [1, 25], "orientation": "Horizontal (normal)", "exposureProgram": "Program AE", "dateTimeOriginal": "Sun Feb 12 12:16:47 2017", "date": "Sun Feb 12 12:16:47 2017", "dateTimeFile": "Tue Sep 22 09:45:12 2020", "size": [1024, 683], "name": "Spot LED 60W 01.jpg", "copyright": "Creative Commons BY-SA 4.0", "artist": "Philippe Teuwen &lt;phil@teuwen.org&gt;", "focalLength": [24, 1], "make": "Canon", "flash": "Off, Did not fire", "sceneCaptureType": "Standard", "dateTime": "Sun Feb 12 23:00:06 2017", "exposureCompensation": [1, 3], "iso": 320, "aperture": [196608, 65536], "meteringMode": "Center-weighted average", "model": "Canon EOS 5D Mark II"}, {"exposureTime": [1, 25], "orientation": "Horizontal (normal)", "exposureProgram": "Program AE", "dateTimeOriginal": "Sun Feb 12 12:17:02 2017", "date": "Sun Feb 12 12:17:02 2017", "dateTimeFile": "Tue Sep 22 09:45:12 2020", "size": [1024, 683], "name": "Spot LED 60W 02.jpg", "copyright": "Creative Commons BY-SA 4.0", "artist": "Philippe Teuwen &lt;phil@teuwen.org&gt;", "focalLength": [24, 1], "make": "Canon", "flash": "Off, Did not fire", "sceneCaptureType": "Standard", "dateTime": "Sun Feb 12 23:03:16 2017", "exposureCompensation": [1, 3], "iso": 500, "aperture": [196608, 65536], "meteringMode": "Center-weighted average", "model": "Canon EOS 5D Mark II"}, {"exposureTime": [1, 20], "orientation": "Horizontal (normal)", "exposureProgram": "Program AE", "dateTimeOriginal": "Sun Feb 12 12:17:22 2017", "date": "Sun Feb 12 12:17:22 2017", "dateTimeFile": "Tue Sep 22 09:45:12 2020", "size": [1024, 683], "name": "Spot LED 60W 03.jpg", "copyright": "Creative Commons BY-SA 4.0", "artist": "Philippe Teuwen &lt;phil@teuwen.org&gt;", "focalLength": [24, 1], "make": "Canon", "flash": "Off, Did not fire", "sceneCaptureType": "Standard", "dateTime": "Sun Feb 12 23:01:10 2017", "exposureCompensation": [1, 3], "iso": 1250, "aperture": [196608, 65536], "meteringMode": "Center-weighted average", "model": "Canon EOS 5D Mark II"}, {"exposureTime": [1, 60], "orientation": "Horizontal (normal)", "exposureProgram": "Program AE", "dateTimeOriginal": "Sat Feb 11 22:44:28 2017", "date": "Sat Feb 11 22:44:28 2017", "dateTimeFile": "Tue Sep 22 09:45:12 2020", "size": [1024, 683], "name": "Spot LED 60W 04 through ND 3.0.jpg", "copyright": "Creative Commons BY-SA 4.0", "artist": "Philippe Teuwen &lt;phil@teuwen.org&gt;", "focalLength": [55, 1], "make": "Canon", "flash": "Off, Did not fire", "sceneCaptureType": "Standard", "dateTime": "Mon Feb 13 01:07:41 2017", "exposureCompensation": [1, 3], "iso": 250, "aperture": [327680, 65536], "meteringMode": "Center-weighted average", "model": "Canon EOS 5D Mark II"}, {"exposureTime": [16, 10], "orientation": "Horizontal (normal)", "exposureProgram": "Program AE", "dateTimeOriginal": "Mon Feb 13 19:08:29 2017", "date": "Mon Feb 13 19:08:29 2017", "dateTimeFile": "Tue Sep 22 09:45:12 2020", "size": [5616, 3744], "name": "Usage ePP.jpg", "copyright": "Creative Commons BY-SA 4.0", "artist": "Philippe Teuwen &lt;phil@teuwen.org&gt;", "focalLength": [63, 1], "make": "Canon", "flash": "Off, Did not fire", "sceneCaptureType": "Standard", "dateTime": "Mon Feb 13 19:08:29 2017", "exposureCompensation": [0, 1], "iso": 3200, "aperture": [196608, 65536], "meteringMode": "Center-weighted average", "model": "Canon EOS 5D Mark II"}]}